zipfile_inflate64/__init__.py
zipfile_inflate64/_inflate64.py
zipfile_inflate64/_patcher.py
zipfile_inflate64/_zipfile.py
zipfile_inflate64/version.py
zipfile_inflate64-0.1.dist-info/METADATA
zipfile_inflate64-0.1.dist-info/WHEEL
zipfile_inflate64-0.1.dist-info/top_level.txt
zipfile_inflate64-0.1.dist-info/RECORD
